rngtestlib/__init__.py
rngtestlib/rngtestlib.py
rngtestlib/testing_suites/ent
rngtestlib/testing_suites/pr
rngtestlib/testing_suites/testu
rngtestlib/testing_suites/sts-2.1.2/assess
rngtestlib/testing_suites/sts-2.1.2/makefile
rngtestlib/testing_suites/sts-2.1.2/data/BBS.dat
rngtestlib/testing_suites/sts-2.1.2/data/data.bad_rng
rngtestlib/testing_suites/sts-2.1.2/data/data.e
rngtestlib/testing_suites/sts-2.1.2/data/data.pi
rngtestlib/testing_suites/sts-2.1.2/data/data.sha1
rngtestlib/testing_suites/sts-2.1.2/data/data.sqrt2
rngtestlib/testing_suites/sts-2.1.2/data/data.sqrt3
rngtestlib/testing_suites/sts-2.1.2/experiments/create-dir-script
rngtestlib/testing_suites/sts-2.1.2/experiments/AlgorithmTesting/finalAnalysisReport.txt
rngtestlib/testing_suites/sts-2.1.2/experiments/AlgorithmTesting/freq.txt
rngtestlib/testing_suites/sts-2.1.2/experiments/AlgorithmTesting/ApproximateEntropy/results.txt
rngtestlib/testing_suites/sts-2.1.2/experiments/AlgorithmTesting/ApproximateEntropy/stats.txt
rngtestlib/testing_suites/sts-2.1.2/experiments/AlgorithmTesting/BlockFrequency/results.txt
rngtestlib/testing_suites/sts-2.1.2/experiments/AlgorithmTesting/BlockFrequency/stats.txt
rngtestlib/testing_suites/sts-2.1.2/experiments/AlgorithmTesting/CumulativeSums/data1.txt
rngtestlib/testing_suites/sts-2.1.2/experiments/AlgorithmTesting/CumulativeSums/data2.txt
rngtestlib/testing_suites/sts-2.1.2/experiments/AlgorithmTesting/CumulativeSums/results.txt
rngtestlib/testing_suites/sts-2.1.2/experiments/AlgorithmTesting/CumulativeSums/stats.txt
rngtestlib/testing_suites/sts-2.1.2/experiments/AlgorithmTesting/FFT/results.txt
rngtestlib/testing_suites/sts-2.1.2/experiments/AlgorithmTesting/FFT/stats.txt
rngtestlib/testing_suites/sts-2.1.2/experiments/AlgorithmTesting/Frequency/results.txt
rngtestlib/testing_suites/sts-2.1.2/experiments/AlgorithmTesting/Frequency/stats.txt
rngtestlib/testing_suites/sts-2.1.2/experiments/AlgorithmTesting/LinearComplexity/results.txt
rngtestlib-0.0.9.dist-info/LICENSE
rngtestlib-0.0.9.dist-info/METADATA
rngtestlib-0.0.9.dist-info/WHEEL
rngtestlib-0.0.9.dist-info/entry_points.txt
rngtestlib-0.0.9.dist-info/top_level.txt
rngtestlib-0.0.9.dist-info/RECORD
